examples/__init__.py
examples/distributed_quantum_phase_estimation.py
examples/phase_kickback.py
examples/template.py
interlinq/__init__.py
interlinq/components/__init__.py
interlinq/components/clock.py
interlinq/components/computing_host.py
interlinq/components/controller_host.py
interlinq/objects/__init__.py
interlinq/objects/circuit.py
interlinq/objects/layer.py
interlinq/objects/operation.py
interlinq/objects/qubit.py
interlinq/utils/__init__.py
interlinq/utils/constants.py
interlinq/utils/default_operation_time.py
tests/__init__.py
tests/test_circuit.py
tests/test_controller_host.py
tests/test_distributed_cnot.py
tests/test_layer.py
tests/test_operation.py
tests/test_template.py
interlin_q-0.0.1.post5.dist-info/LICENSE
interlin_q-0.0.1.post5.dist-info/METADATA
interlin_q-0.0.1.post5.dist-info/WHEEL
interlin_q-0.0.1.post5.dist-info/top_level.txt
interlin_q-0.0.1.post5.dist-info/RECORD
