Metadata-Version: 2.1
Name: interlin-q
Version: 0.0.1.post5
Summary: A Distributed Quantum Computing Framework
Home-page: https://github.com/Interlin-q/Interlin-q
Author: Rhea Parekh, Stephen DiAdamo
Author-email: stephen.diadamo@gmail.com
License: MIT
Download-URL: https://github.com/Interlin-q/Interlin-q/releases/tag/0.0.1
Keywords: quantum,distributed,simulator,computing,Interlin-q
Platform: UNKNOWN
Classifier: Development Status :: 3 - Alpha
Classifier: Intended Audience :: Developers
Classifier: Topic :: Software Development :: Build Tools
Classifier: License :: OSI Approved :: MIT License
Classifier: Operating System :: OS Independent
Classifier: Programming Language :: Python :: 3
Classifier: Programming Language :: Python :: 3.6
Requires-Python: >=3.6
Requires-Dist: qunetsim
